{
"description" : "",
"GsonAgent" : 
 [ 
  {"clss":"BaselGovt","json":"{\"country\":\"Erewhon\",\"capitalPct\":10.0,\"reservePct\":10,\"reserveControls\":true,\"capitalControls\":false,\"payUnemployment\":true,\"unemploymentPayment\":4,\"personalTaxRate\":0,\"corporateTaxRate\":50,\"personalCutoff\":0,\"corporateCutoff\":200,\"maxCivilServants\":0,\"treasuryRate\":10.0,\"minWage\":1,\"name\":\"Erewhon\",\"initialDeposit\":0,\"bankname\":\"Central Bank\",\"x\":0.0,\"y\":0.0,\"defaultProb\":0.0,\"regionName\":\"\"}"},
 {"clss":"Bank","json":"{\"sharePrice\":10,\"capitalPct\":0.2,\"capitalDividend\":0.0,\"capitalSteps\":12,\"interestRateDelta\":0,\"writeOffLimit\":6,\"lossProvisionPct\":0.01,\"labourInput\":0,\"name\":\"Bank-4\",\"initialDeposit\":0,\"bankname\":\"\",\"x\":363.0,\"y\":409.5,\"defaultProb\":0.0,\"regionName\":\"\"}"},
  {"clss":"LabourMarket","json":"{\"maxEmployees\":1,\"bidEqualsAsk\":false,\"maxInventory\":20,\"ttl\":-1,\"minSpread\":1,\"maxSpread\":5,\"minCapital\":200,\"payDividend\":false,\"product\":\"Labour\",\"labourInput\":0,\"name\":\"Labour\",\"initialDeposit\":0,\"bankname\":\"Central Bank\",\"x\":333.0,\"y\":369.5,\"defaultProb\":0.0,\"regionName\":\"\"}"},
  {"clss":"Market","json":"{\"maxEmployees\":5,\"bidEqualsAsk\":false,\"maxInventory\":200,\"ttl\":-1,\"minSpread\":1,\"maxSpread\":2,\"minCapital\":1000,\"payDividend\":false,\"product\":\"Food\",\"labourInput\":0,\"name\":\"M-Food\",\"initialDeposit\":100,\"bankname\":\"Bank-4\",\"x\":333.0,\"y\":369.5,\"defaultProb\":0.0,\"regionName\":\"\"}"},
  {"clss":"Market","json":"{\"maxEmployees\":5,\"bidEqualsAsk\":false,\"maxInventory\":200,\"ttl\":-1,\"minSpread\":1,\"maxSpread\":2,\"minCapital\":1000,\"payDividend\":false,\"product\":\"Milk\",\"labourInput\":0,\"name\":\"M-Milk\",\"initialDeposit\":100,\"bankname\":\"Bank-4\",\"x\":333.0,\"y\":369.5,\"defaultProb\":0.0,\"regionName\":\"\"}"},
  {"clss":"Farm","json":"{\"product\":\"Food\",\"labourInput\":2,\"name\":\"Farm-5\",\"initialDeposit\":100,\"bankname\":\"Bank-4\",\"x\":53.0,\"y\":109.0,\"defaultProb\":0.0,\"regionName\":\"\"}"},
  {"clss":"Farm","json":"{\"product\":\"Milk\",\"labourInput\":2,\"name\":\"Farm-7\",\"initialDeposit\":100,\"bankname\":\"Bank-4\",\"x\":96.0,\"y\":216.0,\"defaultProb\":0.0,\"regionName\":\"\"}"},
  {"clss":"Farm","json":"{\"product\":\"Food\",\"labourInput\":2,\"name\":\"Farm-9\",\"initialDeposit\":100,\"bankname\":\"Bank-4\",\"x\":195.0,\"y\":152.0,\"defaultProb\":0.0,\"regionName\":\"\"}"},
  {"clss":"Farm","json":"{\"product\":\"Milk\",\"labourInput\":2,\"name\":\"Farm-8\",\"initialDeposit\":100,\"bankname\":\"Bank-4\",\"x\":58.0,\"y\":228.0,\"defaultProb\":0.0,\"regionName\":\"\"}"},
  {"clss":"Person","json":"{\"profile\":{\"needs\":{\"Food\":{\"product\":\"Food\",\"quantity\":5,\"storeQ\":5,\"consumption\":2,\"stepFrequency\":0,\"useLoan\":false,\"consumable\":true},\"Milk\":{\"product\":\"Milk\",\"quantity\":5,\"storeQ\":5,\"consumption\":2,\"stepFrequency\":0,\"useLoan\":false,\"consumable\":true}}},\"desiredSalary\":1,\"randomPurchase\":true,\"name\":\"ID-102\",\"initialDeposit\":100,\"bankname\":\"Bank-4\",\"x\":0.0,\"y\":0.0,\"defaultProb\":0.0,\"regionName\":\"\"}"},
  {"clss":"Person","json":"{\"profile\":{\"needs\":{\"Food\":{\"product\":\"Food\",\"quantity\":5,\"storeQ\":5,\"consumption\":2,\"stepFrequency\":0,\"useLoan\":false,\"consumable\":true},\"Milk\":{\"product\":\"Milk\",\"quantity\":5,\"storeQ\":5,\"consumption\":2,\"stepFrequency\":0,\"useLoan\":false,\"consumable\":true}}},\"desiredSalary\":1,\"randomPurchase\":true,\"name\":\"ID-87\",\"initialDeposit\":100,\"bankname\":\"Bank-4\",\"x\":0.0,\"y\":0.0,\"defaultProb\":0.0,\"regionName\":\"\"}"},
  {"clss":"Person","json":"{\"profile\":{\"needs\":{\"Food\":{\"product\":\"Food\",\"quantity\":5,\"storeQ\":5,\"consumption\":2,\"stepFrequency\":0,\"useLoan\":false,\"consumable\":true},\"Milk\":{\"product\":\"Milk\",\"quantity\":5,\"storeQ\":5,\"consumption\":2,\"stepFrequency\":0,\"useLoan\":false,\"consumable\":true}}},\"desiredSalary\":1,\"randomPurchase\":true,\"name\":\"ID-33\",\"initialDeposit\":100,\"bankname\":\"Bank-4\",\"x\":0.0,\"y\":0.0,\"defaultProb\":0.0,\"regionName\":\"\"}"},
  {"clss":"Person","json":"{\"profile\":{\"needs\":{\"Food\":{\"product\":\"Food\",\"quantity\":5,\"storeQ\":5,\"consumption\":2,\"stepFrequency\":0,\"useLoan\":false,\"consumable\":true},\"Milk\":{\"product\":\"Milk\",\"quantity\":5,\"storeQ\":5,\"consumption\":2,\"stepFrequency\":0,\"useLoan\":false,\"consumable\":true}}},\"desiredSalary\":1,\"randomPurchase\":true,\"name\":\"ID-99\",\"initialDeposit\":100,\"bankname\":\"Bank-4\",\"x\":0.0,\"y\":0.0,\"defaultProb\":0.0,\"regionName\":\"\"}"},
  {"clss":"Person","json":"{\"profile\":{\"needs\":{\"Food\":{\"product\":\"Food\",\"quantity\":5,\"storeQ\":5,\"consumption\":2,\"stepFrequency\":0,\"useLoan\":false,\"consumable\":true},\"Milk\":{\"product\":\"Milk\",\"quantity\":5,\"storeQ\":5,\"consumption\":2,\"stepFrequency\":0,\"useLoan\":false,\"consumable\":true}}},\"desiredSalary\":1,\"randomPurchase\":true,\"name\":\"ID-83\",\"initialDeposit\":100,\"bankname\":\"Bank-4\",\"x\":0.0,\"y\":0.0,\"defaultProb\":0.0,\"regionName\":\"\"}"},
  {"clss":"Person","json":"{\"profile\":{\"needs\":{\"Food\":{\"product\":\"Food\",\"quantity\":5,\"storeQ\":5,\"consumption\":2,\"stepFrequency\":0,\"useLoan\":false,\"consumable\":true},\"Milk\":{\"product\":\"Milk\",\"quantity\":5,\"storeQ\":5,\"consumption\":2,\"stepFrequency\":0,\"useLoan\":false,\"consumable\":true}}},\"desiredSalary\":1,\"randomPurchase\":true,\"name\":\"ID-12\",\"initialDeposit\":100,\"bankname\":\"Bank-4\",\"x\":0.0,\"y\":0.0,\"defaultProb\":0.0,\"regionName\":\"\"}"},
  {"clss":"Person","json":"{\"profile\":{\"needs\":{\"Food\":{\"product\":\"Food\",\"quantity\":5,\"storeQ\":5,\"consumption\":2,\"stepFrequency\":0,\"useLoan\":false,\"consumable\":true},\"Milk\":{\"product\":\"Milk\",\"quantity\":5,\"storeQ\":5,\"consumption\":2,\"stepFrequency\":0,\"useLoan\":false,\"consumable\":true}}},\"desiredSalary\":1,\"randomPurchase\":true,\"name\":\"ID-34\",\"initialDeposit\":100,\"bankname\":\"Bank-4\",\"x\":0.0,\"y\":0.0,\"defaultProb\":0.0,\"regionName\":\"\"}"},
  {"clss":"Person","json":"{\"profile\":{\"needs\":{\"Food\":{\"product\":\"Food\",\"quantity\":5,\"storeQ\":5,\"consumption\":2,\"stepFrequency\":0,\"useLoan\":false,\"consumable\":true},\"Milk\":{\"product\":\"Milk\",\"quantity\":5,\"storeQ\":5,\"consumption\":2,\"stepFrequency\":0,\"useLoan\":false,\"consumable\":true}}},\"desiredSalary\":1,\"randomPurchase\":true,\"name\":\"ID-36\",\"initialDeposit\":100,\"bankname\":\"Bank-4\",\"x\":0.0,\"y\":0.0,\"defaultProb\":0.0,\"regionName\":\"\"}"},
  {"clss":"Person","json":"{\"profile\":{\"needs\":{\"Food\":{\"product\":\"Food\",\"quantity\":5,\"storeQ\":5,\"consumption\":2,\"stepFrequency\":0,\"useLoan\":false,\"consumable\":true},\"Milk\":{\"product\":\"Milk\",\"quantity\":5,\"storeQ\":5,\"consumption\":2,\"stepFrequency\":0,\"useLoan\":false,\"consumable\":true}}},\"desiredSalary\":1,\"randomPurchase\":true,\"name\":\"ID-23\",\"initialDeposit\":100,\"bankname\":\"Bank-4\",\"x\":0.0,\"y\":0.0,\"defaultProb\":0.0,\"regionName\":\"\"}"},
  {"clss":"Person","json":"{\"profile\":{\"needs\":{\"Food\":{\"product\":\"Food\",\"quantity\":5,\"storeQ\":5,\"consumption\":2,\"stepFrequency\":0,\"useLoan\":false,\"consumable\":true},\"Milk\":{\"product\":\"Milk\",\"quantity\":5,\"storeQ\":5,\"consumption\":2,\"stepFrequency\":0,\"useLoan\":false,\"consumable\":true}}},\"desiredSalary\":1,\"randomPurchase\":true,\"name\":\"ID-50\",\"initialDeposit\":100,\"bankname\":\"Bank-4\",\"x\":0.0,\"y\":0.0,\"defaultProb\":0.0,\"regionName\":\"\"}"},
  {"clss":"Person","json":"{\"profile\":{\"needs\":{\"Food\":{\"product\":\"Food\",\"quantity\":5,\"storeQ\":5,\"consumption\":2,\"stepFrequency\":0,\"useLoan\":false,\"consumable\":true},\"Milk\":{\"product\":\"Milk\",\"quantity\":5,\"storeQ\":5,\"consumption\":2,\"stepFrequency\":0,\"useLoan\":false,\"consumable\":true}}},\"desiredSalary\":1,\"randomPurchase\":true,\"name\":\"ID-40\",\"initialDeposit\":100,\"bankname\":\"Bank-4\",\"x\":0.0,\"y\":0.0,\"defaultProb\":0.0,\"regionName\":\"\"}"},
  {"clss":"Person","json":"{\"profile\":{\"needs\":{\"Food\":{\"product\":\"Food\",\"quantity\":5,\"storeQ\":5,\"consumption\":2,\"stepFrequency\":0,\"useLoan\":false,\"consumable\":true},\"Milk\":{\"product\":\"Milk\",\"quantity\":5,\"storeQ\":5,\"consumption\":2,\"stepFrequency\":0,\"useLoan\":false,\"consumable\":true}}},\"desiredSalary\":1,\"randomPurchase\":true,\"name\":\"ID-84\",\"initialDeposit\":100,\"bankname\":\"Bank-4\",\"x\":0.0,\"y\":0.0,\"defaultProb\":0.0,\"regionName\":\"\"}"},
  {"clss":"Person","json":"{\"profile\":{\"needs\":{\"Food\":{\"product\":\"Food\",\"quantity\":5,\"storeQ\":5,\"consumption\":2,\"stepFrequency\":0,\"useLoan\":false,\"consumable\":true},\"Milk\":{\"product\":\"Milk\",\"quantity\":5,\"storeQ\":5,\"consumption\":2,\"stepFrequency\":0,\"useLoan\":false,\"consumable\":true}}},\"desiredSalary\":1,\"randomPurchase\":true,\"name\":\"ID-81\",\"initialDeposit\":100,\"bankname\":\"Bank-4\",\"x\":0.0,\"y\":0.0,\"defaultProb\":0.0,\"regionName\":\"\"}"},
  {"clss":"Person","json":"{\"profile\":{\"needs\":{\"Food\":{\"product\":\"Food\",\"quantity\":5,\"storeQ\":5,\"consumption\":2,\"stepFrequency\":0,\"useLoan\":false,\"consumable\":true},\"Milk\":{\"product\":\"Milk\",\"quantity\":5,\"storeQ\":5,\"consumption\":2,\"stepFrequency\":0,\"useLoan\":false,\"consumable\":true}}},\"desiredSalary\":1,\"randomPurchase\":true,\"name\":\"ID-110\",\"initialDeposit\":100,\"bankname\":\"Bank-4\",\"x\":0.0,\"y\":0.0,\"defaultProb\":0.0,\"regionName\":\"\"}"},
  {"clss":"Person","json":"{\"profile\":{\"needs\":{\"Food\":{\"product\":\"Food\",\"quantity\":5,\"storeQ\":5,\"consumption\":2,\"stepFrequency\":0,\"useLoan\":false,\"consumable\":true},\"Milk\":{\"product\":\"Milk\",\"quantity\":5,\"storeQ\":5,\"consumption\":2,\"stepFrequency\":0,\"useLoan\":false,\"consumable\":true}}},\"desiredSalary\":1,\"randomPurchase\":true,\"name\":\"ID-26\",\"initialDeposit\":100,\"bankname\":\"Bank-4\",\"x\":0.0,\"y\":0.0,\"defaultProb\":0.0,\"regionName\":\"\"}"},
  {"clss":"Person","json":"{\"profile\":{\"needs\":{\"Food\":{\"product\":\"Food\",\"quantity\":5,\"storeQ\":5,\"consumption\":2,\"stepFrequency\":0,\"useLoan\":false,\"consumable\":true},\"Milk\":{\"product\":\"Milk\",\"quantity\":5,\"storeQ\":5,\"consumption\":2,\"stepFrequency\":0,\"useLoan\":false,\"consumable\":true}}},\"desiredSalary\":1,\"randomPurchase\":true,\"name\":\"ID-107\",\"initialDeposit\":100,\"bankname\":\"Bank-4\",\"x\":0.0,\"y\":0.0,\"defaultProb\":0.0,\"regionName\":\"\"}"},
  {"clss":"Person","json":"{\"profile\":{\"needs\":{\"Food\":{\"product\":\"Food\",\"quantity\":5,\"storeQ\":5,\"consumption\":2,\"stepFrequency\":0,\"useLoan\":false,\"consumable\":true},\"Milk\":{\"product\":\"Milk\",\"quantity\":5,\"storeQ\":5,\"consumption\":2,\"stepFrequency\":0,\"useLoan\":false,\"consumable\":true}}},\"desiredSalary\":1,\"randomPurchase\":true,\"name\":\"ID-16\",\"initialDeposit\":100,\"bankname\":\"Bank-4\",\"x\":0.0,\"y\":0.0,\"defaultProb\":0.0,\"regionName\":\"\"}"},
  {"clss":"Person","json":"{\"profile\":{\"needs\":{\"Food\":{\"product\":\"Food\",\"quantity\":5,\"storeQ\":5,\"consumption\":2,\"stepFrequency\":0,\"useLoan\":false,\"consumable\":true},\"Milk\":{\"product\":\"Milk\",\"quantity\":5,\"storeQ\":5,\"consumption\":2,\"stepFrequency\":0,\"useLoan\":false,\"consumable\":true}}},\"desiredSalary\":1,\"randomPurchase\":true,\"name\":\"ID-47\",\"initialDeposit\":100,\"bankname\":\"Bank-4\",\"x\":0.0,\"y\":0.0,\"defaultProb\":0.0,\"regionName\":\"\"}"},
  {"clss":"Person","json":"{\"profile\":{\"needs\":{\"Food\":{\"product\":\"Food\",\"quantity\":5,\"storeQ\":5,\"consumption\":2,\"stepFrequency\":0,\"useLoan\":false,\"consumable\":true},\"Milk\":{\"product\":\"Milk\",\"quantity\":5,\"storeQ\":5,\"consumption\":2,\"stepFrequency\":0,\"useLoan\":false,\"consumable\":true}}},\"desiredSalary\":1,\"randomPurchase\":true,\"name\":\"ID-29\",\"initialDeposit\":100,\"bankname\":\"Bank-4\",\"x\":0.0,\"y\":0.0,\"defaultProb\":0.0,\"regionName\":\"\"}"},
  {"clss":"Person","json":"{\"profile\":{\"needs\":{\"Food\":{\"product\":\"Food\",\"quantity\":5,\"storeQ\":5,\"consumption\":2,\"stepFrequency\":0,\"useLoan\":false,\"consumable\":true},\"Milk\":{\"product\":\"Milk\",\"quantity\":5,\"storeQ\":5,\"consumption\":2,\"stepFrequency\":0,\"useLoan\":false,\"consumable\":true}}},\"desiredSalary\":1,\"randomPurchase\":true,\"name\":\"ID-67\",\"initialDeposit\":100,\"bankname\":\"Bank-4\",\"x\":0.0,\"y\":0.0,\"defaultProb\":0.0,\"regionName\":\"\"}"},
  {"clss":"Person","json":"{\"profile\":{\"needs\":{\"Food\":{\"product\":\"Food\",\"quantity\":5,\"storeQ\":5,\"consumption\":2,\"stepFrequency\":0,\"useLoan\":false,\"consumable\":true},\"Milk\":{\"product\":\"Milk\",\"quantity\":5,\"storeQ\":5,\"consumption\":2,\"stepFrequency\":0,\"useLoan\":false,\"consumable\":true}}},\"desiredSalary\":1,\"randomPurchase\":true,\"name\":\"ID-39\",\"initialDeposit\":100,\"bankname\":\"Bank-4\",\"x\":0.0,\"y\":0.0,\"defaultProb\":0.0,\"regionName\":\"\"}"},
  {"clss":"Person","json":"{\"profile\":{\"needs\":{\"Food\":{\"product\":\"Food\",\"quantity\":5,\"storeQ\":5,\"consumption\":2,\"stepFrequency\":0,\"useLoan\":false,\"consumable\":true},\"Milk\":{\"product\":\"Milk\",\"quantity\":5,\"storeQ\":5,\"consumption\":2,\"stepFrequency\":0,\"useLoan\":false,\"consumable\":true}}},\"desiredSalary\":1,\"randomPurchase\":true,\"name\":\"ID-78\",\"initialDeposit\":100,\"bankname\":\"Bank-4\",\"x\":0.0,\"y\":0.0,\"defaultProb\":0.0,\"regionName\":\"\"}"},
  {"clss":"Person","json":"{\"profile\":{\"needs\":{\"Food\":{\"product\":\"Food\",\"quantity\":5,\"storeQ\":5,\"consumption\":2,\"stepFrequency\":0,\"useLoan\":false,\"consumable\":true},\"Milk\":{\"product\":\"Milk\",\"quantity\":5,\"storeQ\":5,\"consumption\":2,\"stepFrequency\":0,\"useLoan\":false,\"consumable\":true}}},\"desiredSalary\":1,\"randomPurchase\":true,\"name\":\"ID-71\",\"initialDeposit\":100,\"bankname\":\"Bank-4\",\"x\":0.0,\"y\":0.0,\"defaultProb\":0.0,\"regionName\":\"\"}"},
  {"clss":"Person","json":"{\"profile\":{\"needs\":{\"Food\":{\"product\":\"Food\",\"quantity\":5,\"storeQ\":5,\"consumption\":2,\"stepFrequency\":0,\"useLoan\":false,\"consumable\":true},\"Milk\":{\"product\":\"Milk\",\"quantity\":5,\"storeQ\":5,\"consumption\":2,\"stepFrequency\":0,\"useLoan\":false,\"consumable\":true}}},\"desiredSalary\":1,\"randomPurchase\":true,\"name\":\"ID-89\",\"initialDeposit\":100,\"bankname\":\"Bank-4\",\"x\":0.0,\"y\":0.0,\"defaultProb\":0.0,\"regionName\":\"\"}"},
  {"clss":"Person","json":"{\"profile\":{\"needs\":{\"Food\":{\"product\":\"Food\",\"quantity\":5,\"storeQ\":5,\"consumption\":2,\"stepFrequency\":0,\"useLoan\":false,\"consumable\":true},\"Milk\":{\"product\":\"Milk\",\"quantity\":5,\"storeQ\":5,\"consumption\":2,\"stepFrequency\":0,\"useLoan\":false,\"consumable\":true}}},\"desiredSalary\":1,\"randomPurchase\":true,\"name\":\"ID-54\",\"initialDeposit\":100,\"bankname\":\"Bank-4\",\"x\":0.0,\"y\":0.0,\"defaultProb\":0.0,\"regionName\":\"\"}"},
  {"clss":"Person","json":"{\"profile\":{\"needs\":{\"Food\":{\"product\":\"Food\",\"quantity\":5,\"storeQ\":5,\"consumption\":2,\"stepFrequency\":0,\"useLoan\":false,\"consumable\":true},\"Milk\":{\"product\":\"Milk\",\"quantity\":5,\"storeQ\":5,\"consumption\":2,\"stepFrequency\":0,\"useLoan\":false,\"consumable\":true}}},\"desiredSalary\":1,\"randomPurchase\":true,\"name\":\"ID-32\",\"initialDeposit\":100,\"bankname\":\"Bank-4\",\"x\":0.0,\"y\":0.0,\"defaultProb\":0.0,\"regionName\":\"\"}"},
  {"clss":"Person","json":"{\"profile\":{\"needs\":{\"Food\":{\"product\":\"Food\",\"quantity\":5,\"storeQ\":5,\"consumption\":2,\"stepFrequency\":0,\"useLoan\":false,\"consumable\":true},\"Milk\":{\"product\":\"Milk\",\"quantity\":5,\"storeQ\":5,\"consumption\":2,\"stepFrequency\":0,\"useLoan\":false,\"consumable\":true}}},\"desiredSalary\":1,\"randomPurchase\":true,\"name\":\"ID-79\",\"initialDeposit\":100,\"bankname\":\"Bank-4\",\"x\":0.0,\"y\":0.0,\"defaultProb\":0.0,\"regionName\":\"\"}"},
  {"clss":"Person","json":"{\"profile\":{\"needs\":{\"Food\":{\"product\":\"Food\",\"quantity\":5,\"storeQ\":5,\"consumption\":2,\"stepFrequency\":0,\"useLoan\":false,\"consumable\":true},\"Milk\":{\"product\":\"Milk\",\"quantity\":5,\"storeQ\":5,\"consumption\":2,\"stepFrequency\":0,\"useLoan\":false,\"consumable\":true}}},\"desiredSalary\":1,\"randomPurchase\":true,\"name\":\"ID-62\",\"initialDeposit\":100,\"bankname\":\"Bank-4\",\"x\":0.0,\"y\":0.0,\"defaultProb\":0.0,\"regionName\":\"\"}"},
  {"clss":"Person","json":"{\"profile\":{\"needs\":{\"Food\":{\"product\":\"Food\",\"quantity\":5,\"storeQ\":5,\"consumption\":2,\"stepFrequency\":0,\"useLoan\":false,\"consumable\":true},\"Milk\":{\"product\":\"Milk\",\"quantity\":5,\"storeQ\":5,\"consumption\":2,\"stepFrequency\":0,\"useLoan\":false,\"consumable\":true}}},\"desiredSalary\":1,\"randomPurchase\":true,\"name\":\"ID-49\",\"initialDeposit\":100,\"bankname\":\"Bank-4\",\"x\":0.0,\"y\":0.0,\"defaultProb\":0.0,\"regionName\":\"\"}"},
  {"clss":"Person","json":"{\"profile\":{\"needs\":{\"Food\":{\"product\":\"Food\",\"quantity\":5,\"storeQ\":5,\"consumption\":2,\"stepFrequency\":0,\"useLoan\":false,\"consumable\":true},\"Milk\":{\"product\":\"Milk\",\"quantity\":5,\"storeQ\":5,\"consumption\":2,\"stepFrequency\":0,\"useLoan\":false,\"consumable\":true}}},\"desiredSalary\":1,\"randomPurchase\":true,\"name\":\"ID-35\",\"initialDeposit\":100,\"bankname\":\"Bank-4\",\"x\":0.0,\"y\":0.0,\"defaultProb\":0.0,\"regionName\":\"\"}"},
  {"clss":"Person","json":"{\"profile\":{\"needs\":{\"Food\":{\"product\":\"Food\",\"quantity\":5,\"storeQ\":5,\"consumption\":2,\"stepFrequency\":0,\"useLoan\":false,\"consumable\":true},\"Milk\":{\"product\":\"Milk\",\"quantity\":5,\"storeQ\":5,\"consumption\":2,\"stepFrequency\":0,\"useLoan\":false,\"consumable\":true}}},\"desiredSalary\":1,\"randomPurchase\":true,\"name\":\"ID-18\",\"initialDeposit\":100,\"bankname\":\"Bank-4\",\"x\":0.0,\"y\":0.0,\"defaultProb\":0.0,\"regionName\":\"\"}"},
  {"clss":"Person","json":"{\"profile\":{\"needs\":{\"Food\":{\"product\":\"Food\",\"quantity\":5,\"storeQ\":5,\"consumption\":2,\"stepFrequency\":0,\"useLoan\":false,\"consumable\":true},\"Milk\":{\"product\":\"Milk\",\"quantity\":5,\"storeQ\":5,\"consumption\":2,\"stepFrequency\":0,\"useLoan\":false,\"consumable\":true}}},\"desiredSalary\":1,\"randomPurchase\":true,\"name\":\"ID-106\",\"initialDeposit\":100,\"bankname\":\"Bank-4\",\"x\":0.0,\"y\":0.0,\"defaultProb\":0.0,\"regionName\":\"\"}"},
  {"clss":"Person","json":"{\"profile\":{\"needs\":{\"Food\":{\"product\":\"Food\",\"quantity\":5,\"storeQ\":5,\"consumption\":2,\"stepFrequency\":0,\"useLoan\":false,\"consumable\":true},\"Milk\":{\"product\":\"Milk\",\"quantity\":5,\"storeQ\":5,\"consumption\":2,\"stepFrequency\":0,\"useLoan\":false,\"consumable\":true}}},\"desiredSalary\":1,\"randomPurchase\":true,\"name\":\"ID-15\",\"initialDeposit\":100,\"bankname\":\"Bank-4\",\"x\":0.0,\"y\":0.0,\"defaultProb\":0.0,\"regionName\":\"\"}"},
  {"clss":"Person","json":"{\"profile\":{\"needs\":{\"Food\":{\"product\":\"Food\",\"quantity\":5,\"storeQ\":5,\"consumption\":2,\"stepFrequency\":0,\"useLoan\":false,\"consumable\":true},\"Milk\":{\"product\":\"Milk\",\"quantity\":5,\"storeQ\":5,\"consumption\":2,\"stepFrequency\":0,\"useLoan\":false,\"consumable\":true}}},\"desiredSalary\":1,\"randomPurchase\":true,\"name\":\"ID-74\",\"initialDeposit\":100,\"bankname\":\"Bank-4\",\"x\":0.0,\"y\":0.0,\"defaultProb\":0.0,\"regionName\":\"\"}"},
  {"clss":"Person","json":"{\"profile\":{\"needs\":{\"Food\":{\"product\":\"Food\",\"quantity\":5,\"storeQ\":5,\"consumption\":2,\"stepFrequency\":0,\"useLoan\":false,\"consumable\":true},\"Milk\":{\"product\":\"Milk\",\"quantity\":5,\"storeQ\":5,\"consumption\":2,\"stepFrequency\":0,\"useLoan\":false,\"consumable\":true}}},\"desiredSalary\":1,\"randomPurchase\":true,\"name\":\"ID-52\",\"initialDeposit\":100,\"bankname\":\"Bank-4\",\"x\":0.0,\"y\":0.0,\"defaultProb\":0.0,\"regionName\":\"\"}"},
  {"clss":"Person","json":"{\"profile\":{\"needs\":{\"Food\":{\"product\":\"Food\",\"quantity\":5,\"storeQ\":5,\"consumption\":2,\"stepFrequency\":0,\"useLoan\":false,\"consumable\":true},\"Milk\":{\"product\":\"Milk\",\"quantity\":5,\"storeQ\":5,\"consumption\":2,\"stepFrequency\":0,\"useLoan\":false,\"consumable\":true}}},\"desiredSalary\":1,\"randomPurchase\":true,\"name\":\"ID-45\",\"initialDeposit\":100,\"bankname\":\"Bank-4\",\"x\":0.0,\"y\":0.0,\"defaultProb\":0.0,\"regionName\":\"\"}"},
  {"clss":"Person","json":"{\"profile\":{\"needs\":{\"Food\":{\"product\":\"Food\",\"quantity\":5,\"storeQ\":5,\"consumption\":2,\"stepFrequency\":0,\"useLoan\":false,\"consumable\":true},\"Milk\":{\"product\":\"Milk\",\"quantity\":5,\"storeQ\":5,\"consumption\":2,\"stepFrequency\":0,\"useLoan\":false,\"consumable\":true}}},\"desiredSalary\":1,\"randomPurchase\":true,\"name\":\"ID-94\",\"initialDeposit\":100,\"bankname\":\"Bank-4\",\"x\":0.0,\"y\":0.0,\"defaultProb\":0.0,\"regionName\":\"\"}"},
  {"clss":"Person","json":"{\"profile\":{\"needs\":{\"Food\":{\"product\":\"Food\",\"quantity\":5,\"storeQ\":5,\"consumption\":2,\"stepFrequency\":0,\"useLoan\":false,\"consumable\":true},\"Milk\":{\"product\":\"Milk\",\"quantity\":5,\"storeQ\":5,\"consumption\":2,\"stepFrequency\":0,\"useLoan\":false,\"consumable\":true}}},\"desiredSalary\":1,\"randomPurchase\":true,\"name\":\"ID-55\",\"initialDeposit\":100,\"bankname\":\"Bank-4\",\"x\":0.0,\"y\":0.0,\"defaultProb\":0.0,\"regionName\":\"\"}"},
  {"clss":"Person","json":"{\"profile\":{\"needs\":{\"Food\":{\"product\":\"Food\",\"quantity\":5,\"storeQ\":5,\"consumption\":2,\"stepFrequency\":0,\"useLoan\":false,\"consumable\":true},\"Milk\":{\"product\":\"Milk\",\"quantity\":5,\"storeQ\":5,\"consumption\":2,\"stepFrequency\":0,\"useLoan\":false,\"consumable\":true}}},\"desiredSalary\":1,\"randomPurchase\":true,\"name\":\"ID-65\",\"initialDeposit\":100,\"bankname\":\"Bank-4\",\"x\":0.0,\"y\":0.0,\"defaultProb\":0.0,\"regionName\":\"\"}"},
  {"clss":"Person","json":"{\"profile\":{\"needs\":{\"Food\":{\"product\":\"Food\",\"quantity\":5,\"storeQ\":5,\"consumption\":2,\"stepFrequency\":0,\"useLoan\":false,\"consumable\":true},\"Milk\":{\"product\":\"Milk\",\"quantity\":5,\"storeQ\":5,\"consumption\":2,\"stepFrequency\":0,\"useLoan\":false,\"consumable\":true}}},\"desiredSalary\":1,\"randomPurchase\":true,\"name\":\"ID-58\",\"initialDeposit\":100,\"bankname\":\"Bank-4\",\"x\":0.0,\"y\":0.0,\"defaultProb\":0.0,\"regionName\":\"\"}"},
  {"clss":"Person","json":"{\"profile\":{\"needs\":{\"Food\":{\"product\":\"Food\",\"quantity\":5,\"storeQ\":5,\"consumption\":2,\"stepFrequency\":0,\"useLoan\":false,\"consumable\":true},\"Milk\":{\"product\":\"Milk\",\"quantity\":5,\"storeQ\":5,\"consumption\":2,\"stepFrequency\":0,\"useLoan\":false,\"consumable\":true}}},\"desiredSalary\":1,\"randomPurchase\":true,\"name\":\"ID-42\",\"initialDeposit\":100,\"bankname\":\"Bank-4\",\"x\":0.0,\"y\":0.0,\"defaultProb\":0.0,\"regionName\":\"\"}"},
  {"clss":"Person","json":"{\"profile\":{\"needs\":{\"Food\":{\"product\":\"Food\",\"quantity\":5,\"storeQ\":5,\"consumption\":2,\"stepFrequency\":0,\"useLoan\":false,\"consumable\":true},\"Milk\":{\"product\":\"Milk\",\"quantity\":5,\"storeQ\":5,\"consumption\":2,\"stepFrequency\":0,\"useLoan\":false,\"consumable\":true}}},\"desiredSalary\":1,\"randomPurchase\":true,\"name\":\"ID-92\",\"initialDeposit\":100,\"bankname\":\"Bank-4\",\"x\":0.0,\"y\":0.0,\"defaultProb\":0.0,\"regionName\":\"\"}"},
  {"clss":"Person","json":"{\"profile\":{\"needs\":{\"Food\":{\"product\":\"Food\",\"quantity\":5,\"storeQ\":5,\"consumption\":2,\"stepFrequency\":0,\"useLoan\":false,\"consumable\":true},\"Milk\":{\"product\":\"Milk\",\"quantity\":5,\"storeQ\":5,\"consumption\":2,\"stepFrequency\":0,\"useLoan\":false,\"consumable\":true}}},\"desiredSalary\":1,\"randomPurchase\":true,\"name\":\"ID-72\",\"initialDeposit\":100,\"bankname\":\"Bank-4\",\"x\":0.0,\"y\":0.0,\"defaultProb\":0.0,\"regionName\":\"\"}"},
  {"clss":"Person","json":"{\"profile\":{\"needs\":{\"Food\":{\"product\":\"Food\",\"quantity\":5,\"storeQ\":5,\"consumption\":2,\"stepFrequency\":0,\"useLoan\":false,\"consumable\":true},\"Milk\":{\"product\":\"Milk\",\"quantity\":5,\"storeQ\":5,\"consumption\":2,\"stepFrequency\":0,\"useLoan\":false,\"consumable\":true}}},\"desiredSalary\":1,\"randomPurchase\":true,\"name\":\"ID-61\",\"initialDeposit\":100,\"bankname\":\"Bank-4\",\"x\":0.0,\"y\":0.0,\"defaultProb\":0.0,\"regionName\":\"\"}"},
  {"clss":"Person","json":"{\"profile\":{\"needs\":{\"Food\":{\"product\":\"Food\",\"quantity\":5,\"storeQ\":5,\"consumption\":2,\"stepFrequency\":0,\"useLoan\":false,\"consumable\":true},\"Milk\":{\"product\":\"Milk\",\"quantity\":5,\"storeQ\":5,\"consumption\":2,\"stepFrequency\":0,\"useLoan\":false,\"consumable\":true}}},\"desiredSalary\":1,\"randomPurchase\":true,\"name\":\"ID-97\",\"initialDeposit\":100,\"bankname\":\"Bank-4\",\"x\":0.0,\"y\":0.0,\"defaultProb\":0.0,\"regionName\":\"\"}"},
  {"clss":"Person","json":"{\"profile\":{\"needs\":{\"Food\":{\"product\":\"Food\",\"quantity\":5,\"storeQ\":5,\"consumption\":2,\"stepFrequency\":0,\"useLoan\":false,\"consumable\":true},\"Milk\":{\"product\":\"Milk\",\"quantity\":5,\"storeQ\":5,\"consumption\":2,\"stepFrequency\":0,\"useLoan\":false,\"consumable\":true}}},\"desiredSalary\":1,\"randomPurchase\":true,\"name\":\"ID-31\",\"initialDeposit\":100,\"bankname\":\"Bank-4\",\"x\":0.0,\"y\":0.0,\"defaultProb\":0.0,\"regionName\":\"\"}"},
  {"clss":"Person","json":"{\"profile\":{\"needs\":{\"Food\":{\"product\":\"Food\",\"quantity\":5,\"storeQ\":5,\"consumption\":2,\"stepFrequency\":0,\"useLoan\":false,\"consumable\":true},\"Milk\":{\"product\":\"Milk\",\"quantity\":5,\"storeQ\":5,\"consumption\":2,\"stepFrequency\":0,\"useLoan\":false,\"consumable\":true}}},\"desiredSalary\":1,\"randomPurchase\":true,\"name\":\"ID-69\",\"initialDeposit\":100,\"bankname\":\"Bank-4\",\"x\":0.0,\"y\":0.0,\"defaultProb\":0.0,\"regionName\":\"\"}"},
  {"clss":"Person","json":"{\"profile\":{\"needs\":{\"Food\":{\"product\":\"Food\",\"quantity\":5,\"storeQ\":5,\"consumption\":2,\"stepFrequency\":0,\"useLoan\":false,\"consumable\":true},\"Milk\":{\"product\":\"Milk\",\"quantity\":5,\"storeQ\":5,\"consumption\":2,\"stepFrequency\":0,\"useLoan\":false,\"consumable\":true}}},\"desiredSalary\":1,\"randomPurchase\":true,\"name\":\"ID-46\",\"initialDeposit\":100,\"bankname\":\"Bank-4\",\"x\":0.0,\"y\":0.0,\"defaultProb\":0.0,\"regionName\":\"\"}"},
  {"clss":"Person","json":"{\"profile\":{\"needs\":{\"Food\":{\"product\":\"Food\",\"quantity\":5,\"storeQ\":5,\"consumption\":2,\"stepFrequency\":0,\"useLoan\":false,\"consumable\":true},\"Milk\":{\"product\":\"Milk\",\"quantity\":5,\"storeQ\":5,\"consumption\":2,\"stepFrequency\":0,\"useLoan\":false,\"consumable\":true}}},\"desiredSalary\":1,\"randomPurchase\":true,\"name\":\"ID-43\",\"initialDeposit\":100,\"bankname\":\"Bank-4\",\"x\":0.0,\"y\":0.0,\"defaultProb\":0.0,\"regionName\":\"\"}"},
  {"clss":"Person","json":"{\"profile\":{\"needs\":{\"Food\":{\"product\":\"Food\",\"quantity\":5,\"storeQ\":5,\"consumption\":2,\"stepFrequency\":0,\"useLoan\":false,\"consumable\":true},\"Milk\":{\"product\":\"Milk\",\"quantity\":5,\"storeQ\":5,\"consumption\":2,\"stepFrequency\":0,\"useLoan\":false,\"consumable\":true}}},\"desiredSalary\":1,\"randomPurchase\":true,\"name\":\"ID-19\",\"initialDeposit\":100,\"bankname\":\"Bank-4\",\"x\":0.0,\"y\":0.0,\"defaultProb\":0.0,\"regionName\":\"\"}"},
  {"clss":"Person","json":"{\"profile\":{\"needs\":{\"Food\":{\"product\":\"Food\",\"quantity\":5,\"storeQ\":5,\"consumption\":2,\"stepFrequency\":0,\"useLoan\":false,\"consumable\":true},\"Milk\":{\"product\":\"Milk\",\"quantity\":5,\"storeQ\":5,\"consumption\":2,\"stepFrequency\":0,\"useLoan\":false,\"consumable\":true}}},\"desiredSalary\":1,\"randomPurchase\":true,\"name\":\"ID-11\",\"initialDeposit\":100,\"bankname\":\"Bank-4\",\"x\":0.0,\"y\":0.0,\"defaultProb\":0.0,\"regionName\":\"\"}"},
  {"clss":"Person","json":"{\"profile\":{\"needs\":{\"Food\":{\"product\":\"Food\",\"quantity\":5,\"storeQ\":5,\"consumption\":2,\"stepFrequency\":0,\"useLoan\":false,\"consumable\":true},\"Milk\":{\"product\":\"Milk\",\"quantity\":5,\"storeQ\":5,\"consumption\":2,\"stepFrequency\":0,\"useLoan\":false,\"consumable\":true}}},\"desiredSalary\":1,\"randomPurchase\":true,\"name\":\"ID-56\",\"initialDeposit\":100,\"bankname\":\"Bank-4\",\"x\":0.0,\"y\":0.0,\"defaultProb\":0.0,\"regionName\":\"\"}"},
  {"clss":"Person","json":"{\"profile\":{\"needs\":{\"Food\":{\"product\":\"Food\",\"quantity\":5,\"storeQ\":5,\"consumption\":2,\"stepFrequency\":0,\"useLoan\":false,\"consumable\":true},\"Milk\":{\"product\":\"Milk\",\"quantity\":5,\"storeQ\":5,\"consumption\":2,\"stepFrequency\":0,\"useLoan\":false,\"consumable\":true}}},\"desiredSalary\":1,\"randomPurchase\":true,\"name\":\"ID-20\",\"initialDeposit\":100,\"bankname\":\"Bank-4\",\"x\":0.0,\"y\":0.0,\"defaultProb\":0.0,\"regionName\":\"\"}"},
  {"clss":"Person","json":"{\"profile\":{\"needs\":{\"Food\":{\"product\":\"Food\",\"quantity\":5,\"storeQ\":5,\"consumption\":2,\"stepFrequency\":0,\"useLoan\":false,\"consumable\":true},\"Milk\":{\"product\":\"Milk\",\"quantity\":5,\"storeQ\":5,\"consumption\":2,\"stepFrequency\":0,\"useLoan\":false,\"consumable\":true}}},\"desiredSalary\":1,\"randomPurchase\":true,\"name\":\"ID-66\",\"initialDeposit\":100,\"bankname\":\"Bank-4\",\"x\":0.0,\"y\":0.0,\"defaultProb\":0.0,\"regionName\":\"\"}"},
  {"clss":"Person","json":"{\"profile\":{\"needs\":{\"Food\":{\"product\":\"Food\",\"quantity\":5,\"storeQ\":5,\"consumption\":2,\"stepFrequency\":0,\"useLoan\":false,\"consumable\":true},\"Milk\":{\"product\":\"Milk\",\"quantity\":5,\"storeQ\":5,\"consumption\":2,\"stepFrequency\":0,\"useLoan\":false,\"consumable\":true}}},\"desiredSalary\":1,\"randomPurchase\":true,\"name\":\"ID-109\",\"initialDeposit\":100,\"bankname\":\"Bank-4\",\"x\":0.0,\"y\":0.0,\"defaultProb\":0.0,\"regionName\":\"\"}"},
  {"clss":"Person","json":"{\"profile\":{\"needs\":{\"Food\":{\"product\":\"Food\",\"quantity\":5,\"storeQ\":5,\"consumption\":2,\"stepFrequency\":0,\"useLoan\":false,\"consumable\":true},\"Milk\":{\"product\":\"Milk\",\"quantity\":5,\"storeQ\":5,\"consumption\":2,\"stepFrequency\":0,\"useLoan\":false,\"consumable\":true}}},\"desiredSalary\":1,\"randomPurchase\":true,\"name\":\"ID-63\",\"initialDeposit\":100,\"bankname\":\"Bank-4\",\"x\":0.0,\"y\":0.0,\"defaultProb\":0.0,\"regionName\":\"\"}"},
  {"clss":"Person","json":"{\"profile\":{\"needs\":{\"Food\":{\"product\":\"Food\",\"quantity\":5,\"storeQ\":5,\"consumption\":2,\"stepFrequency\":0,\"useLoan\":false,\"consumable\":true},\"Milk\":{\"product\":\"Milk\",\"quantity\":5,\"storeQ\":5,\"consumption\":2,\"stepFrequency\":0,\"useLoan\":false,\"consumable\":true}}},\"desiredSalary\":1,\"randomPurchase\":true,\"name\":\"ID-70\",\"initialDeposit\":100,\"bankname\":\"Bank-4\",\"x\":0.0,\"y\":0.0,\"defaultProb\":0.0,\"regionName\":\"\"}"},
  {"clss":"Person","json":"{\"profile\":{\"needs\":{\"Food\":{\"product\":\"Food\",\"quantity\":5,\"storeQ\":5,\"consumption\":2,\"stepFrequency\":0,\"useLoan\":false,\"consumable\":true},\"Milk\":{\"product\":\"Milk\",\"quantity\":5,\"storeQ\":5,\"consumption\":2,\"stepFrequency\":0,\"useLoan\":false,\"consumable\":true}}},\"desiredSalary\":1,\"randomPurchase\":true,\"name\":\"ID-30\",\"initialDeposit\":100,\"bankname\":\"Bank-4\",\"x\":0.0,\"y\":0.0,\"defaultProb\":0.0,\"regionName\":\"\"}"},
  {"clss":"Person","json":"{\"profile\":{\"needs\":{\"Food\":{\"product\":\"Food\",\"quantity\":5,\"storeQ\":5,\"consumption\":2,\"stepFrequency\":0,\"useLoan\":false,\"consumable\":true},\"Milk\":{\"product\":\"Milk\",\"quantity\":5,\"storeQ\":5,\"consumption\":2,\"stepFrequency\":0,\"useLoan\":false,\"consumable\":true}}},\"desiredSalary\":1,\"randomPurchase\":true,\"name\":\"ID-13\",\"initialDeposit\":100,\"bankname\":\"Bank-4\",\"x\":0.0,\"y\":0.0,\"defaultProb\":0.0,\"regionName\":\"\"}"},
  {"clss":"Person","json":"{\"profile\":{\"needs\":{\"Food\":{\"product\":\"Food\",\"quantity\":5,\"storeQ\":5,\"consumption\":2,\"stepFrequency\":0,\"useLoan\":false,\"consumable\":true},\"Milk\":{\"product\":\"Milk\",\"quantity\":5,\"storeQ\":5,\"consumption\":2,\"stepFrequency\":0,\"useLoan\":false,\"consumable\":true}}},\"desiredSalary\":1,\"randomPurchase\":true,\"name\":\"ID-17\",\"initialDeposit\":100,\"bankname\":\"Bank-4\",\"x\":0.0,\"y\":0.0,\"defaultProb\":0.0,\"regionName\":\"\"}"},
  {"clss":"Person","json":"{\"profile\":{\"needs\":{\"Food\":{\"product\":\"Food\",\"quantity\":5,\"storeQ\":5,\"consumption\":2,\"stepFrequency\":0,\"useLoan\":false,\"consumable\":true},\"Milk\":{\"product\":\"Milk\",\"quantity\":5,\"storeQ\":5,\"consumption\":2,\"stepFrequency\":0,\"useLoan\":false,\"consumable\":true}}},\"desiredSalary\":1,\"randomPurchase\":true,\"name\":\"ID-104\",\"initialDeposit\":100,\"bankname\":\"Bank-4\",\"x\":0.0,\"y\":0.0,\"defaultProb\":0.0,\"regionName\":\"\"}"},
  {"clss":"Person","json":"{\"profile\":{\"needs\":{\"Food\":{\"product\":\"Food\",\"quantity\":5,\"storeQ\":5,\"consumption\":2,\"stepFrequency\":0,\"useLoan\":false,\"consumable\":true},\"Milk\":{\"product\":\"Milk\",\"quantity\":5,\"storeQ\":5,\"consumption\":2,\"stepFrequency\":0,\"useLoan\":false,\"consumable\":true}}},\"desiredSalary\":1,\"randomPurchase\":true,\"name\":\"ID-80\",\"initialDeposit\":100,\"bankname\":\"Bank-4\",\"x\":0.0,\"y\":0.0,\"defaultProb\":0.0,\"regionName\":\"\"}"},
  {"clss":"Person","json":"{\"profile\":{\"needs\":{\"Food\":{\"product\":\"Food\",\"quantity\":5,\"storeQ\":5,\"consumption\":2,\"stepFrequency\":0,\"useLoan\":false,\"consumable\":true},\"Milk\":{\"product\":\"Milk\",\"quantity\":5,\"storeQ\":5,\"consumption\":2,\"stepFrequency\":0,\"useLoan\":false,\"consumable\":true}}},\"desiredSalary\":1,\"randomPurchase\":true,\"name\":\"ID-85\",\"initialDeposit\":100,\"bankname\":\"Bank-4\",\"x\":0.0,\"y\":0.0,\"defaultProb\":0.0,\"regionName\":\"\"}"},
  {"clss":"Person","json":"{\"profile\":{\"needs\":{\"Food\":{\"product\":\"Food\",\"quantity\":5,\"storeQ\":5,\"consumption\":2,\"stepFrequency\":0,\"useLoan\":false,\"consumable\":true},\"Milk\":{\"product\":\"Milk\",\"quantity\":5,\"storeQ\":5,\"consumption\":2,\"stepFrequency\":0,\"useLoan\":false,\"consumable\":true}}},\"desiredSalary\":1,\"randomPurchase\":true,\"name\":\"ID-90\",\"initialDeposit\":100,\"bankname\":\"Bank-4\",\"x\":0.0,\"y\":0.0,\"defaultProb\":0.0,\"regionName\":\"\"}"},
  {"clss":"Person","json":"{\"profile\":{\"needs\":{\"Food\":{\"product\":\"Food\",\"quantity\":5,\"storeQ\":5,\"consumption\":2,\"stepFrequency\":0,\"useLoan\":false,\"consumable\":true},\"Milk\":{\"product\":\"Milk\",\"quantity\":5,\"storeQ\":5,\"consumption\":2,\"stepFrequency\":0,\"useLoan\":false,\"consumable\":true}}},\"desiredSalary\":1,\"randomPurchase\":true,\"name\":\"ID-27\",\"initialDeposit\":100,\"bankname\":\"Bank-4\",\"x\":0.0,\"y\":0.0,\"defaultProb\":0.0,\"regionName\":\"\"}"},
  {"clss":"Person","json":"{\"profile\":{\"needs\":{\"Food\":{\"product\":\"Food\",\"quantity\":5,\"storeQ\":5,\"consumption\":2,\"stepFrequency\":0,\"useLoan\":false,\"consumable\":true},\"Milk\":{\"product\":\"Milk\",\"quantity\":5,\"storeQ\":5,\"consumption\":2,\"stepFrequency\":0,\"useLoan\":false,\"consumable\":true}}},\"desiredSalary\":1,\"randomPurchase\":true,\"name\":\"ID-93\",\"initialDeposit\":100,\"bankname\":\"Bank-4\",\"x\":0.0,\"y\":0.0,\"defaultProb\":0.0,\"regionName\":\"\"}"},
  {"clss":"Person","json":"{\"profile\":{\"needs\":{\"Food\":{\"product\":\"Food\",\"quantity\":5,\"storeQ\":5,\"consumption\":2,\"stepFrequency\":0,\"useLoan\":false,\"consumable\":true},\"Milk\":{\"product\":\"Milk\",\"quantity\":5,\"storeQ\":5,\"consumption\":2,\"stepFrequency\":0,\"useLoan\":false,\"consumable\":true}}},\"desiredSalary\":1,\"randomPurchase\":true,\"name\":\"ID-77\",\"initialDeposit\":100,\"bankname\":\"Bank-4\",\"x\":0.0,\"y\":0.0,\"defaultProb\":0.0,\"regionName\":\"\"}"},
  {"clss":"Person","json":"{\"profile\":{\"needs\":{\"Food\":{\"product\":\"Food\",\"quantity\":5,\"storeQ\":5,\"consumption\":2,\"stepFrequency\":0,\"useLoan\":false,\"consumable\":true},\"Milk\":{\"product\":\"Milk\",\"quantity\":5,\"storeQ\":5,\"consumption\":2,\"stepFrequency\":0,\"useLoan\":false,\"consumable\":true}}},\"desiredSalary\":1,\"randomPurchase\":true,\"name\":\"ID-73\",\"initialDeposit\":100,\"bankname\":\"Bank-4\",\"x\":0.0,\"y\":0.0,\"defaultProb\":0.0,\"regionName\":\"\"}"},
  {"clss":"Person","json":"{\"profile\":{\"needs\":{\"Food\":{\"product\":\"Food\",\"quantity\":5,\"storeQ\":5,\"consumption\":2,\"stepFrequency\":0,\"useLoan\":false,\"consumable\":true},\"Milk\":{\"product\":\"Milk\",\"quantity\":5,\"storeQ\":5,\"consumption\":2,\"stepFrequency\":0,\"useLoan\":false,\"consumable\":true}}},\"desiredSalary\":1,\"randomPurchase\":true,\"name\":\"ID-100\",\"initialDeposit\":100,\"bankname\":\"Bank-4\",\"x\":0.0,\"y\":0.0,\"defaultProb\":0.0,\"regionName\":\"\"}"},
  {"clss":"Person","json":"{\"profile\":{\"needs\":{\"Food\":{\"product\":\"Food\",\"quantity\":5,\"storeQ\":5,\"consumption\":2,\"stepFrequency\":0,\"useLoan\":false,\"consumable\":true},\"Milk\":{\"product\":\"Milk\",\"quantity\":5,\"storeQ\":5,\"consumption\":2,\"stepFrequency\":0,\"useLoan\":false,\"consumable\":true}}},\"desiredSalary\":1,\"randomPurchase\":true,\"name\":\"ID-105\",\"initialDeposit\":100,\"bankname\":\"Bank-4\",\"x\":0.0,\"y\":0.0,\"defaultProb\":0.0,\"regionName\":\"\"}"},
  {"clss":"Person","json":"{\"profile\":{\"needs\":{\"Food\":{\"product\":\"Food\",\"quantity\":5,\"storeQ\":5,\"consumption\":2,\"stepFrequency\":0,\"useLoan\":false,\"consumable\":true},\"Milk\":{\"product\":\"Milk\",\"quantity\":5,\"storeQ\":5,\"consumption\":2,\"stepFrequency\":0,\"useLoan\":false,\"consumable\":true}}},\"desiredSalary\":1,\"randomPurchase\":true,\"name\":\"ID-51\",\"initialDeposit\":100,\"bankname\":\"Bank-4\",\"x\":0.0,\"y\":0.0,\"defaultProb\":0.0,\"regionName\":\"\"}"},
  {"clss":"Person","json":"{\"profile\":{\"needs\":{\"Food\":{\"product\":\"Food\",\"quantity\":5,\"storeQ\":5,\"consumption\":2,\"stepFrequency\":0,\"useLoan\":false,\"consumable\":true},\"Milk\":{\"product\":\"Milk\",\"quantity\":5,\"storeQ\":5,\"consumption\":2,\"stepFrequency\":0,\"useLoan\":false,\"consumable\":true}}},\"desiredSalary\":1,\"randomPurchase\":true,\"name\":\"ID-25\",\"initialDeposit\":100,\"bankname\":\"Bank-4\",\"x\":0.0,\"y\":0.0,\"defaultProb\":0.0,\"regionName\":\"\"}"},
  {"clss":"Person","json":"{\"profile\":{\"needs\":{\"Food\":{\"product\":\"Food\",\"quantity\":5,\"storeQ\":5,\"consumption\":2,\"stepFrequency\":0,\"useLoan\":false,\"consumable\":true},\"Milk\":{\"product\":\"Milk\",\"quantity\":5,\"storeQ\":5,\"consumption\":2,\"stepFrequency\":0,\"useLoan\":false,\"consumable\":true}}},\"desiredSalary\":1,\"randomPurchase\":true,\"name\":\"ID-95\",\"initialDeposit\":100,\"bankname\":\"Bank-4\",\"x\":0.0,\"y\":0.0,\"defaultProb\":0.0,\"regionName\":\"\"}"},
  {"clss":"Person","json":"{\"profile\":{\"needs\":{\"Food\":{\"product\":\"Food\",\"quantity\":5,\"storeQ\":5,\"consumption\":2,\"stepFrequency\":0,\"useLoan\":false,\"consumable\":true},\"Milk\":{\"product\":\"Milk\",\"quantity\":5,\"storeQ\":5,\"consumption\":2,\"stepFrequency\":0,\"useLoan\":false,\"consumable\":true}}},\"desiredSalary\":1,\"randomPurchase\":true,\"name\":\"ID-59\",\"initialDeposit\":100,\"bankname\":\"Bank-4\",\"x\":0.0,\"y\":0.0,\"defaultProb\":0.0,\"regionName\":\"\"}"},
  {"clss":"Person","json":"{\"profile\":{\"needs\":{\"Food\":{\"product\":\"Food\",\"quantity\":5,\"storeQ\":5,\"consumption\":2,\"stepFrequency\":0,\"useLoan\":false,\"consumable\":true},\"Milk\":{\"product\":\"Milk\",\"quantity\":5,\"storeQ\":5,\"consumption\":2,\"stepFrequency\":0,\"useLoan\":false,\"consumable\":true}}},\"desiredSalary\":1,\"randomPurchase\":true,\"name\":\"ID-60\",\"initialDeposit\":100,\"bankname\":\"Bank-4\",\"x\":0.0,\"y\":0.0,\"defaultProb\":0.0,\"regionName\":\"\"}"},
  {"clss":"Person","json":"{\"profile\":{\"needs\":{\"Food\":{\"product\":\"Food\",\"quantity\":5,\"storeQ\":5,\"consumption\":2,\"stepFrequency\":0,\"useLoan\":false,\"consumable\":true},\"Milk\":{\"product\":\"Milk\",\"quantity\":5,\"storeQ\":5,\"consumption\":2,\"stepFrequency\":0,\"useLoan\":false,\"consumable\":true}}},\"desiredSalary\":1,\"randomPurchase\":true,\"name\":\"ID-64\",\"initialDeposit\":100,\"bankname\":\"Bank-4\",\"x\":0.0,\"y\":0.0,\"defaultProb\":0.0,\"regionName\":\"\"}"},
  {"clss":"Person","json":"{\"profile\":{\"needs\":{\"Food\":{\"product\":\"Food\",\"quantity\":5,\"storeQ\":5,\"consumption\":2,\"stepFrequency\":0,\"useLoan\":false,\"consumable\":true},\"Milk\":{\"product\":\"Milk\",\"quantity\":5,\"storeQ\":5,\"consumption\":2,\"stepFrequency\":0,\"useLoan\":false,\"consumable\":true}}},\"desiredSalary\":1,\"randomPurchase\":true,\"name\":\"ID-96\",\"initialDeposit\":100,\"bankname\":\"Bank-4\",\"x\":0.0,\"y\":0.0,\"defaultProb\":0.0,\"regionName\":\"\"}"},
  {"clss":"Person","json":"{\"profile\":{\"needs\":{\"Food\":{\"product\":\"Food\",\"quantity\":5,\"storeQ\":5,\"consumption\":2,\"stepFrequency\":0,\"useLoan\":false,\"consumable\":true},\"Milk\":{\"product\":\"Milk\",\"quantity\":5,\"storeQ\":5,\"consumption\":2,\"stepFrequency\":0,\"useLoan\":false,\"consumable\":true}}},\"desiredSalary\":1,\"randomPurchase\":true,\"name\":\"ID-53\",\"initialDeposit\":100,\"bankname\":\"Bank-4\",\"x\":0.0,\"y\":0.0,\"defaultProb\":0.0,\"regionName\":\"\"}"},
  {"clss":"Person","json":"{\"profile\":{\"needs\":{\"Food\":{\"product\":\"Food\",\"quantity\":5,\"storeQ\":5,\"consumption\":2,\"stepFrequency\":0,\"useLoan\":false,\"consumable\":true},\"Milk\":{\"product\":\"Milk\",\"quantity\":5,\"storeQ\":5,\"consumption\":2,\"stepFrequency\":0,\"useLoan\":false,\"consumable\":true}}},\"desiredSalary\":1,\"randomPurchase\":true,\"name\":\"ID-41\",\"initialDeposit\":100,\"bankname\":\"Bank-4\",\"x\":0.0,\"y\":0.0,\"defaultProb\":0.0,\"regionName\":\"\"}"},
  {"clss":"Person","json":"{\"profile\":{\"needs\":{\"Food\":{\"product\":\"Food\",\"quantity\":5,\"storeQ\":5,\"consumption\":2,\"stepFrequency\":0,\"useLoan\":false,\"consumable\":true},\"Milk\":{\"product\":\"Milk\",\"quantity\":5,\"storeQ\":5,\"consumption\":2,\"stepFrequency\":0,\"useLoan\":false,\"consumable\":true}}},\"desiredSalary\":1,\"randomPurchase\":true,\"name\":\"ID-75\",\"initialDeposit\":100,\"bankname\":\"Bank-4\",\"x\":0.0,\"y\":0.0,\"defaultProb\":0.0,\"regionName\":\"\"}"},
  {"clss":"Person","json":"{\"profile\":{\"needs\":{\"Food\":{\"product\":\"Food\",\"quantity\":5,\"storeQ\":5,\"consumption\":2,\"stepFrequency\":0,\"useLoan\":false,\"consumable\":true},\"Milk\":{\"product\":\"Milk\",\"quantity\":5,\"storeQ\":5,\"consumption\":2,\"stepFrequency\":0,\"useLoan\":false,\"consumable\":true}}},\"desiredSalary\":1,\"randomPurchase\":true,\"name\":\"ID-91\",\"initialDeposit\":100,\"bankname\":\"Bank-4\",\"x\":0.0,\"y\":0.0,\"defaultProb\":0.0,\"regionName\":\"\"}"},
  {"clss":"Person","json":"{\"profile\":{\"needs\":{\"Food\":{\"product\":\"Food\",\"quantity\":5,\"storeQ\":5,\"consumption\":2,\"stepFrequency\":0,\"useLoan\":false,\"consumable\":true},\"Milk\":{\"product\":\"Milk\",\"quantity\":5,\"storeQ\":5,\"consumption\":2,\"stepFrequency\":0,\"useLoan\":false,\"consumable\":true}}},\"desiredSalary\":1,\"randomPurchase\":true,\"name\":\"ID-103\",\"initialDeposit\":100,\"bankname\":\"Bank-4\",\"x\":0.0,\"y\":0.0,\"defaultProb\":0.0,\"regionName\":\"\"}"},
  {"clss":"Person","json":"{\"profile\":{\"needs\":{\"Food\":{\"product\":\"Food\",\"quantity\":5,\"storeQ\":5,\"consumption\":2,\"stepFrequency\":0,\"useLoan\":false,\"consumable\":true},\"Milk\":{\"product\":\"Milk\",\"quantity\":5,\"storeQ\":5,\"consumption\":2,\"stepFrequency\":0,\"useLoan\":false,\"consumable\":true}}},\"desiredSalary\":1,\"randomPurchase\":true,\"name\":\"ID-44\",\"initialDeposit\":100,\"bankname\":\"Bank-4\",\"x\":0.0,\"y\":0.0,\"defaultProb\":0.0,\"regionName\":\"\"}"},
  {"clss":"Person","json":"{\"profile\":{\"needs\":{\"Food\":{\"product\":\"Food\",\"quantity\":5,\"storeQ\":5,\"consumption\":2,\"stepFrequency\":0,\"useLoan\":false,\"consumable\":true},\"Milk\":{\"product\":\"Milk\",\"quantity\":5,\"storeQ\":5,\"consumption\":2,\"stepFrequency\":0,\"useLoan\":false,\"consumable\":true}}},\"desiredSalary\":1,\"randomPurchase\":true,\"name\":\"ID-68\",\"initialDeposit\":100,\"bankname\":\"Bank-4\",\"x\":0.0,\"y\":0.0,\"defaultProb\":0.0,\"regionName\":\"\"}"},
  {"clss":"Person","json":"{\"profile\":{\"needs\":{\"Food\":{\"product\":\"Food\",\"quantity\":5,\"storeQ\":5,\"consumption\":2,\"stepFrequency\":0,\"useLoan\":false,\"consumable\":true},\"Milk\":{\"product\":\"Milk\",\"quantity\":5,\"storeQ\":5,\"consumption\":2,\"stepFrequency\":0,\"useLoan\":false,\"consumable\":true}}},\"desiredSalary\":1,\"randomPurchase\":true,\"name\":\"ID-82\",\"initialDeposit\":100,\"bankname\":\"Bank-4\",\"x\":0.0,\"y\":0.0,\"defaultProb\":0.0,\"regionName\":\"\"}"},
  {"clss":"Person","json":"{\"profile\":{\"needs\":{\"Food\":{\"product\":\"Food\",\"quantity\":5,\"storeQ\":5,\"consumption\":2,\"stepFrequency\":0,\"useLoan\":false,\"consumable\":true},\"Milk\":{\"product\":\"Milk\",\"quantity\":5,\"storeQ\":5,\"consumption\":2,\"stepFrequency\":0,\"useLoan\":false,\"consumable\":true}}},\"desiredSalary\":1,\"randomPurchase\":true,\"name\":\"ID-37\",\"initialDeposit\":100,\"bankname\":\"Bank-4\",\"x\":0.0,\"y\":0.0,\"defaultProb\":0.0,\"regionName\":\"\"}"},
  {"clss":"Person","json":"{\"profile\":{\"needs\":{\"Food\":{\"product\":\"Food\",\"quantity\":5,\"storeQ\":5,\"consumption\":2,\"stepFrequency\":0,\"useLoan\":false,\"consumable\":true},\"Milk\":{\"product\":\"Milk\",\"quantity\":5,\"storeQ\":5,\"consumption\":2,\"stepFrequency\":0,\"useLoan\":false,\"consumable\":true}}},\"desiredSalary\":1,\"randomPurchase\":true,\"name\":\"ID-24\",\"initialDeposit\":100,\"bankname\":\"Bank-4\",\"x\":0.0,\"y\":0.0,\"defaultProb\":0.0,\"regionName\":\"\"}"},
  {"clss":"Person","json":"{\"profile\":{\"needs\":{\"Food\":{\"product\":\"Food\",\"quantity\":5,\"storeQ\":5,\"consumption\":2,\"stepFrequency\":0,\"useLoan\":false,\"consumable\":true},\"Milk\":{\"product\":\"Milk\",\"quantity\":5,\"storeQ\":5,\"consumption\":2,\"stepFrequency\":0,\"useLoan\":false,\"consumable\":true}}},\"desiredSalary\":1,\"randomPurchase\":true,\"name\":\"ID-48\",\"initialDeposit\":100,\"bankname\":\"Bank-4\",\"x\":0.0,\"y\":0.0,\"defaultProb\":0.0,\"regionName\":\"\"}"},
  {"clss":"Person","json":"{\"profile\":{\"needs\":{\"Food\":{\"product\":\"Food\",\"quantity\":5,\"storeQ\":5,\"consumption\":2,\"stepFrequency\":0,\"useLoan\":false,\"consumable\":true},\"Milk\":{\"product\":\"Milk\",\"quantity\":5,\"storeQ\":5,\"consumption\":2,\"stepFrequency\":0,\"useLoan\":false,\"consumable\":true}}},\"desiredSalary\":1,\"randomPurchase\":true,\"name\":\"ID-14\",\"initialDeposit\":100,\"bankname\":\"Bank-4\",\"x\":0.0,\"y\":0.0,\"defaultProb\":0.0,\"regionName\":\"\"}"},
  {"clss":"Person","json":"{\"profile\":{\"needs\":{\"Food\":{\"product\":\"Food\",\"quantity\":5,\"storeQ\":5,\"consumption\":2,\"stepFrequency\":0,\"useLoan\":false,\"consumable\":true},\"Milk\":{\"product\":\"Milk\",\"quantity\":5,\"storeQ\":5,\"consumption\":2,\"stepFrequency\":0,\"useLoan\":false,\"consumable\":true}}},\"desiredSalary\":1,\"randomPurchase\":true,\"name\":\"ID-21\",\"initialDeposit\":100,\"bankname\":\"Bank-4\",\"x\":0.0,\"y\":0.0,\"defaultProb\":0.0,\"regionName\":\"\"}"},
  {"clss":"Person","json":"{\"profile\":{\"needs\":{\"Food\":{\"product\":\"Food\",\"quantity\":5,\"storeQ\":5,\"consumption\":2,\"stepFrequency\":0,\"useLoan\":false,\"consumable\":true},\"Milk\":{\"product\":\"Milk\",\"quantity\":5,\"storeQ\":5,\"consumption\":2,\"stepFrequency\":0,\"useLoan\":false,\"consumable\":true}}},\"desiredSalary\":1,\"randomPurchase\":true,\"name\":\"ID-108\",\"initialDeposit\":100,\"bankname\":\"Bank-4\",\"x\":0.0,\"y\":0.0,\"defaultProb\":0.0,\"regionName\":\"\"}"},
  {"clss":"Person","json":"{\"profile\":{\"needs\":{\"Food\":{\"product\":\"Food\",\"quantity\":5,\"storeQ\":5,\"consumption\":2,\"stepFrequency\":0,\"useLoan\":false,\"consumable\":true},\"Milk\":{\"product\":\"Milk\",\"quantity\":5,\"storeQ\":5,\"consumption\":2,\"stepFrequency\":0,\"useLoan\":false,\"consumable\":true}}},\"desiredSalary\":1,\"randomPurchase\":true,\"name\":\"ID-101\",\"initialDeposit\":100,\"bankname\":\"Bank-4\",\"x\":0.0,\"y\":0.0,\"defaultProb\":0.0,\"regionName\":\"\"}"},
  {"clss":"Person","json":"{\"profile\":{\"needs\":{\"Food\":{\"product\":\"Food\",\"quantity\":5,\"storeQ\":5,\"consumption\":2,\"stepFrequency\":0,\"useLoan\":false,\"consumable\":true},\"Milk\":{\"product\":\"Milk\",\"quantity\":5,\"storeQ\":5,\"consumption\":2,\"stepFrequency\":0,\"useLoan\":false,\"consumable\":true}}},\"desiredSalary\":1,\"randomPurchase\":true,\"name\":\"ID-22\",\"initialDeposit\":100,\"bankname\":\"Bank-4\",\"x\":0.0,\"y\":0.0,\"defaultProb\":0.0,\"regionName\":\"\"}"},
  {"clss":"Person","json":"{\"profile\":{\"needs\":{\"Food\":{\"product\":\"Food\",\"quantity\":5,\"storeQ\":5,\"consumption\":2,\"stepFrequency\":0,\"useLoan\":false,\"consumable\":true},\"Milk\":{\"product\":\"Milk\",\"quantity\":5,\"storeQ\":5,\"consumption\":2,\"stepFrequency\":0,\"useLoan\":false,\"consumable\":true}}},\"desiredSalary\":1,\"randomPurchase\":true,\"name\":\"ID-98\",\"initialDeposit\":100,\"bankname\":\"Bank-4\",\"x\":0.0,\"y\":0.0,\"defaultProb\":0.0,\"regionName\":\"\"}"},
  {"clss":"Person","json":"{\"profile\":{\"needs\":{\"Food\":{\"product\":\"Food\",\"quantity\":5,\"storeQ\":5,\"consumption\":2,\"stepFrequency\":0,\"useLoan\":false,\"consumable\":true},\"Milk\":{\"product\":\"Milk\",\"quantity\":5,\"storeQ\":5,\"consumption\":2,\"stepFrequency\":0,\"useLoan\":false,\"consumable\":true}}},\"desiredSalary\":1,\"randomPurchase\":true,\"name\":\"ID-76\",\"initialDeposit\":100,\"bankname\":\"Bank-4\",\"x\":0.0,\"y\":0.0,\"defaultProb\":0.0,\"regionName\":\"\"}"},
  {"clss":"Person","json":"{\"profile\":{\"needs\":{\"Food\":{\"product\":\"Food\",\"quantity\":5,\"storeQ\":5,\"consumption\":2,\"stepFrequency\":0,\"useLoan\":false,\"consumable\":true},\"Milk\":{\"product\":\"Milk\",\"quantity\":5,\"storeQ\":5,\"consumption\":2,\"stepFrequency\":0,\"useLoan\":false,\"consumable\":true}}},\"desiredSalary\":1,\"randomPurchase\":true,\"name\":\"ID-57\",\"initialDeposit\":100,\"bankname\":\"Bank-4\",\"x\":0.0,\"y\":0.0,\"defaultProb\":0.0,\"regionName\":\"\"}"},
  {"clss":"Person","json":"{\"profile\":{\"needs\":{\"Food\":{\"product\":\"Food\",\"quantity\":5,\"storeQ\":5,\"consumption\":2,\"stepFrequency\":0,\"useLoan\":false,\"consumable\":true},\"Milk\":{\"product\":\"Milk\",\"quantity\":5,\"storeQ\":5,\"consumption\":2,\"stepFrequency\":0,\"useLoan\":false,\"consumable\":true}}},\"desiredSalary\":1,\"randomPurchase\":true,\"name\":\"ID-88\",\"initialDeposit\":100,\"bankname\":\"Bank-4\",\"x\":0.0,\"y\":0.0,\"defaultProb\":0.0,\"regionName\":\"\"}"},
  {"clss":"Person","json":"{\"profile\":{\"needs\":{\"Food\":{\"product\":\"Food\",\"quantity\":5,\"storeQ\":5,\"consumption\":2,\"stepFrequency\":0,\"useLoan\":false,\"consumable\":true},\"Milk\":{\"product\":\"Milk\",\"quantity\":5,\"storeQ\":5,\"consumption\":2,\"stepFrequency\":0,\"useLoan\":false,\"consumable\":true}}},\"desiredSalary\":1,\"randomPurchase\":true,\"name\":\"ID-86\",\"initialDeposit\":100,\"bankname\":\"Bank-4\",\"x\":0.0,\"y\":0.0,\"defaultProb\":0.0,\"regionName\":\"\"}"},
  {"clss":"Person","json":"{\"profile\":{\"needs\":{\"Food\":{\"product\":\"Food\",\"quantity\":5,\"storeQ\":5,\"consumption\":2,\"stepFrequency\":0,\"useLoan\":false,\"consumable\":true},\"Milk\":{\"product\":\"Milk\",\"quantity\":5,\"storeQ\":5,\"consumption\":2,\"stepFrequency\":0,\"useLoan\":false,\"consumable\":true}}},\"desiredSalary\":1,\"randomPurchase\":true,\"name\":\"ID-38\",\"initialDeposit\":100,\"bankname\":\"Bank-4\",\"x\":0.0,\"y\":0.0,\"defaultProb\":0.0,\"regionName\":\"\"}"},
  {"clss":"Person","json":"{\"profile\":{\"needs\":{\"Food\":{\"product\":\"Food\",\"quantity\":5,\"storeQ\":5,\"consumption\":2,\"stepFrequency\":0,\"useLoan\":false,\"consumable\":true},\"Milk\":{\"product\":\"Milk\",\"quantity\":5,\"storeQ\":5,\"consumption\":2,\"stepFrequency\":0,\"useLoan\":false,\"consumable\":true}}},\"desiredSalary\":1,\"randomPurchase\":true,\"name\":\"ID-28\",\"initialDeposit\":100,\"bankname\":\"Bank-4\",\"x\":0.0,\"y\":0.0,\"defaultProb\":0.0,\"regionName\":\"\"}"}
 ]
}